xmind2testcasezen/__about__.py
xmind2testcasezen/__init__.py
xmind2testcasezen/cli.py
xmind2testcasezen/const.py
xmind2testcasezen/metadata.py
xmind2testcasezen/parse_new.py
xmind2testcasezen/parse_old.py
xmind2testcasezen/parser_xmind.py
xmind2testcasezen/services.py
xmind2testcasezen/testlink.py
xmind2testcasezen/utils.py
xmind2testcasezen/xreader.py
xmind2testcasezen/zenreader.py
xmind2testcasezen/zentao.py
xmind2testcasezen-0.0.6.dist-info/METADATA
xmind2testcasezen-0.0.6.dist-info/WHEEL
xmind2testcasezen-0.0.6.dist-info/entry_points.txt
xmind2testcasezen-0.0.6.dist-info/top_level.txt
xmind2testcasezen-0.0.6.dist-info/RECORD
