Metadata-Version: 2.1
Name: xmind2testcasezen
Version: 0.0.6
Summary: XMind2TestCaseZen基于XMind2TestCase做二次开发，提供了一个高效测试用例设计的解决方案！
Home-page: https://github.com/maiyajj/xmind2testcasezen
Author: maiyajj
Author-email: 
License: MIT
Keywords: xmind2testCase, testcase, test, testing, xmind, 思维导图, XMind思维导图
Classifier: Programming Language :: Python :: 3
Classifier: License :: OSI Approved :: MIT License
Classifier: Operating System :: OS Independent
Requires-Python: >=3.0, <4
Requires-Dist: xmind
Requires-Dist: flask
Requires-Dist: arrow
